pyomapi/__init__.py
pyomapi/auth.py
pyomapi/exceptions.py
pyomapi/message.py
pyomapi/omapi.py
pyomapi/transport.py
pyomapi/utils.py
pyomapi-0.0.1.dist-info/DESCRIPTION.rst
pyomapi-0.0.1.dist-info/METADATA
pyomapi-0.0.1.dist-info/RECORD
pyomapi-0.0.1.dist-info/WHEEL
pyomapi-0.0.1.dist-info/metadata.json
pyomapi-0.0.1.dist-info/top_level.txt
