Metadata-Version: 2.0
Name: pyomapi
Version: 0.0.1
Summary: ISC DHCP OMAPI python client
Home-page: https://github.com/xzased/pyomapi
Author: Ruben Quinones
Author-email: ruben.quinones@rackspace.com
License: Apache-2.0
Platform: UNKNOWN
Classifier: Development Status :: 3 - Alpha
Classifier: Intended Audience :: System Administrators
Classifier: Programming Language :: Python
Classifier: Programming Language :: Python :: 3
Classifier: Programming Language :: Python :: 3.4
Classifier: Programming Language :: Python :: 3.5
Classifier: Programming Language :: Python :: 3.6
Classifier: Topic :: Internet
Classifier: Topic :: System :: Networking
Classifier: Topic :: Software Development :: Libraries :: Python Modules
Requires-Dist: pytest
